adic/__init__.py
adic/_modidx.py
adic/core.py
adic-0.0.1.dist-info/LICENSE
adic-0.0.1.dist-info/METADATA
adic-0.0.1.dist-info/WHEEL
adic-0.0.1.dist-info/entry_points.txt
adic-0.0.1.dist-info/top_level.txt
adic-0.0.1.dist-info/RECORD
