Metadata-Version: 2.1
Name: adic
Version: 0.0.1
Summary: chaos package of utilities; a nod to adiclith
Home-page: https://github.com/dsm-72/adic
Author: dsm-72
Author-email: sumner.magruder@yale.edu
License: Apache Software License 2.0
Keywords: nbdev jupyter notebook python
Classifier: Development Status :: 4 - Beta
Classifier: Intended Audience :: Developers
Classifier: Natural Language :: English
Classifier: Programming Language :: Python :: 3.11
Classifier: License :: OSI Approved :: Apache Software License
Requires-Python: >=3.11
License-File: LICENSE
Requires-Dist: atyp
Requires-Dist: chck
Requires-Dist: mstar
Provides-Extra: dev
